{
  "parent": "minecraft:recipes/root",
  "display": {
    "icon": {
      "id": "additionallanterns:blue_red_nether_bricks_lantern"
    },
    "title": {
      "translate": "additionallanterns.advancement.recipes/misc/red_nether_bricks_lantern_blue.title"
    },
    "description": {
      "translate": "additionallanterns.advancement.recipes/misc/red_nether_bricks_lantern_blue.description"
    },
    "frame": "task",
    "show_toast": false,
    "announce_to_chat": false,
    "hidden": false
  },
  "criteria": {
    "has_the_recipe": {
      "trigger": "minecraft:recipe_unlocked",
      "conditions": {
        "recipe": "additionallanterns:red_nether_bricks_lantern_blue"
      }
    },
    "recipe_condition": {
      "trigger": "minecraft:inventory_changed",
      "conditions": {
        "items": [
          {
            "items": "#additionallanterns:red_nether_bricks_lanterns"
          }
        ]
      }
    }
  },
  "requirements": [
    [
      "has_the_recipe",
      "recipe_condition"
    ]
  ],
  "rewards": {
    "recipes": [
      "additionallanterns:red_nether_bricks_lantern_blue"
    ]
  }
}